pyOffice/__init__.py
pyOffice/__main__.py
py_office-0.1.2.dist-info/LICENSE
py_office-0.1.2.dist-info/METADATA
py_office-0.1.2.dist-info/WHEEL
py_office-0.1.2.dist-info/entry_points.txt
py_office-0.1.2.dist-info/top_level.txt
py_office-0.1.2.dist-info/RECORD
