Metadata-Version: 2.1
Name: py-office
Version: 0.1.2
Summary: py-office is a gui based on python to process data efficienly
Home-page: https://github.com/YC-Lammy/py-office
Author: YC
Author-email: yclam508@protonmail.com
License: GPL
Platform: Linux
Platform: Mac OS X
Platform: Windows
Classifier: License :: OSI Approved :: GNU General Public License v3 (GPLv3)
Classifier: Programming Language :: Python :: 3
Classifier: Programming Language :: Python :: 3.7
Classifier: Programming Language :: Python :: 3.8
Classifier: Programming Language :: Python :: 3.9
Classifier: Programming Language :: Python :: 3 :: Only
Requires-Dist: py-office-learn
Requires-Dist: py-office-sheet
